gpu_coloc/__init__.py
gpu_coloc/cli.py
gpu_coloc/coloc.py
gpu_coloc/format.py
gpu_coloc-0.4.2.dist-info/METADATA
gpu_coloc-0.4.2.dist-info/WHEEL
gpu_coloc-0.4.2.dist-info/entry_points.txt
gpu_coloc-0.4.2.dist-info/top_level.txt
gpu_coloc-0.4.2.dist-info/RECORD
