Metadata-Version: 2.4
Name: gpu-coloc
Version: 0.4.2
Summary: Ultra-fast GPU-enabled Bayesian colocalisation
Home-page: https://github.com/mjesse-github/gpu-coloc
Author: Mihkel Jesse
License: MIT
Requires-Python: >=3.12
Requires-Dist: filelock>=3.17.0
Requires-Dist: fsspec>=2025.2.0
Requires-Dist: Jinja2>=3.1.5
Requires-Dist: MarkupSafe>=3.0.2
Requires-Dist: mpmath>=1.3.0
Requires-Dist: networkx>=3.4.2
Requires-Dist: numpy>=2.2.3
Requires-Dist: pandas>=2.2.3
Requires-Dist: pyarrow>=19.0.0
Requires-Dist: python-dateutil>=2.9.0.post0
Requires-Dist: pytz>=2025.1
Requires-Dist: six>=1.17.0
Requires-Dist: sympy>=1.13.1
Requires-Dist: torch>=2.0
Requires-Dist: tqdm>=4.67.1
Requires-Dist: typing_extensions>=4.12.2
Requires-Dist: tzdata>=2025.1
Dynamic: author
Dynamic: description
Dynamic: description-content-type
Dynamic: home-page
Dynamic: license
Dynamic: requires-dist
Dynamic: requires-python
Dynamic: summary
